untangle_rs-0.2.2.dist-info/METADATA
untangle_rs-0.2.2.dist-info/WHEEL
untangle_rs-0.2.2.dist-info/licenses/LICENSE
untanglers/__init__.py
untanglers/__init__.pyi
untanglers/py.typed
untanglers/untanglers.abi3.so
untangle_rs-0.2.2.dist-info/RECORD
