Metadata-Version: 2.4
Name: untangle-rs
Version: 0.2.2
Classifier: Development Status :: 3 - Alpha
Classifier: Intended Audience :: Developers
Classifier: License :: OSI Approved :: MIT License
Classifier: Natural Language :: English
Classifier: Operating System :: MacOS :: MacOS X
Classifier: Operating System :: Microsoft :: Windows
Classifier: Operating System :: POSIX :: Linux
Classifier: Programming Language :: Python :: 3 :: Only
Classifier: Programming Language :: Python :: 3.11
Classifier: Programming Language :: Python :: 3.12
Classifier: Programming Language :: Python :: 3.13
Classifier: Programming Language :: Python :: 3
Classifier: Programming Language :: Python :: Implementation :: CPython
Classifier: Programming Language :: Rust
Classifier: Topic :: Scientific/Engineering :: Information Analysis
Classifier: Topic :: Scientific/Engineering :: Mathematics
Classifier: Topic :: Scientific/Engineering :: Visualization
Classifier: Topic :: Software Development :: Libraries :: Python Modules
Requires-Dist: maturin>=1.9.1,<2.0.0
License-File: LICENSE
Summary: Library that minimises edge crossings in a hierarchical multipartite graph
Author-email: Matthijs Wesseling <matthijswesseling@gmail.com>
License: MIT
Requires-Python: >=3.11, <4
Project-URL: Homepage, https://github.com/Bladieblah/untangle-rs
Project-URL: Repository, https://github.com/Bladieblah/untangle-rs.git
Project-URL: Bug Tracker, https://github.com/Bladieblah/untangle-rs/issues
